Workbook

Sheet Start here
B2: Investment Cohort progress reports — data template
B3: Fill in one tab per table. Each tab is saved as a CSV (File → Download → CSV, one tab at a time) and uploaded in the report admin.
B5: HOW TO READ THIS FILE
B6: Green header | C6: Required column. Every row needs a value.
B7: Grey header | C7: Optional column. Leave blank if you don't have it.
B8: Header notes | C8: Hover over any column header to see what goes in it.
B9: Grey italic rows | C9: Example rows (the Example Capital / Horizon Ventures demo). Delete them and type your own data over them.
B10: Dropdowns | C10: yes/no, status and ID columns have dropdowns, so IDs always match between tabs.
B11: Dates | C11: Use real dates. They display as YYYY-MM-DD, which is the format the import expects.
B12: Column names | C12: Do not rename, reorder or delete the header row. You may add your own extra columns to the right; they are ignored.
B14: FILL IN THIS ORDER
B15: cohorts | C15: One row per programme cohort.
B16: firms | C16: One row per participating investment firm. Each firm gets one private company report.
B17: fellows | C17: One row per sponsored fellow. Include every fellow in the cohort, even from firms not receiving a report, so cohort averages are correct.
B18: sessions | C18: One row per programme session, including sessions not yet held.
B19: attendance_feedback | C19: One row per fellow per session held. Paste reflections exactly as the fellow wrote them; they are shown word for word.
B20: capstone | C20: Add a NEW row each time a fellow's Capstone status changes (do not overwrite), so earlier reports stay as issued.
B21: self_updates | C21: Checkpoint self updates: one row per fellow per checkpoint, from the fellows' checkpoint tracker. Shown as the "Checkpoint · Self updates" card.
B22: checkpoints | C22: One row per progress report round. A checkpoint fixes which sessions that report covers.
B23: authorised_users | C23: Who may open each firm's report.
B24: check_figures | C24: Not imported. Shows each fellow's attendance and feedback figures so you can sanity-check before uploading.
B26: RULES THAT MATTER
B27: IDs | C27: Choose short IDs once (e.g. firm-acme, fellow-jane-doe, s01) and never change them. Names can change; IDs cannot.
B28: Every fellow, every session | C28: Add one attendance_feedback row for every fellow for every session held, including absences (attended = no). A missing row counts as absent and is flagged.
B29: Reflections | C29: Paste the fellow's answers exactly as submitted. Nothing is rewritten, summarised or generated by AI; the report shows their own words.
B30: Feedback | C30: Feedback only counts for sessions the fellow attended. Feedback completion % = feedback submitted ÷ sessions attended.
B31: Capstone | C31: When a status changes (e.g. pending → complete), add a new row with a new recorded_at date instead of editing the old one.
B32: Checkpoints | C32: Each report round is a checkpoint listing the sessions it covers. Once published, leave it alone and add the next one.
B33: Cohort averages | C33: Include all fellows in the cohort, even if their firm is not receiving a report (set report_enabled = no on that firm).
B34: Links | C34: Leave report_token blank. The system creates the private link codes.
B36: Questions | C36: Full specification: docs/DATA_IMPORT.md in the project repository.

Sheet cohorts
A1: cohort_id | B1: cohort_name | C1: programme_name | D1: start_date | E1: end_date
A2: cohort-2026 | B2: Investment Cohort 2026 | C2: Investment Cohort | D2: 46251 | E2: 46356

Sheet firms
A1: firm_id | B1: firm_name | C1: cohort_id | D1: logo_url | E1: report_token | F1: report_enabled
A2: firm-example-capital | B2: Example Capital | C2: cohort-2026 | F2: yes
A3: firm-horizon-ventures | B3: Horizon Ventures | C3: cohort-2026 | F3: yes

Sheet fellows
A1: fellow_id | B1: first_name | C1: last_name | D1: role | E1: firm_id | F1: cohort_id | G1: report_token
A2: fellow-alexandra-smith | B2: Alexandra | C2: Smith | D2: Investment Associate | E2: firm-example-capital | F2: cohort-2026
A3: fellow-daniel-mensah | B3: Daniel | C3: Mensah | D3: Senior Investment Analyst | E3: firm-example-capital | F3: cohort-2026
A4: fellow-amara-okafor | B4: Amara | C4: Okafor | D4: Principal | E4: firm-horizon-ventures | F4: cohort-2026

Sheet sessions
A1: session_id | B1: cohort_id | C1: session_number | D1: session_title | E1: session_date | F1: status | G1: facilitator
A2: s01 | B2: cohort-2026 | C2: 1 | D2: The state of venture capital in Africa | E2: 46251 | F2: held
A3: s02 | B3: cohort-2026 | C3: 2 | D3: Investment judgement and conviction | E3: 46258 | F3: held
A4: s03 | B4: cohort-2026 | C4: 3 | D4: Sourcing and building a proprietary pipeline | E4: 46265 | F4: held
A5: s04 | B5: cohort-2026 | C5: 4 | D5: Due diligence that changes decisions | E5: 46272 | F5: held
A6: s05 | B6: cohort-2026 | C6: 5 | D6: Valuation and deal structuring | E6: 46279 | F6: held
A7: s06 | B7: cohort-2026 | C7: 6 | D7: Portfolio construction and reserves | E7: 46286 | F7: held
A8: s07 | B8: cohort-2026 | C8: 7 | D8: Working with founders after the cheque | E8: 46293 | F8: held
A9: s08 | B9: cohort-2026 | C9: 8 | D9: Writing for the investment committee | E9: 46300 | F9: held
A10: s09 | B10: cohort-2026 | C10: 9 | D10: Blended and catalytic capital | E10: 46307 | F10: scheduled
A11: s10 | B11: cohort-2026 | C11: 10 | D11: Exits, secondaries and liquidity | E11: 46314 | F11: scheduled
A12: s11 | B12: cohort-2026 | C12: 11 | D12: Raising from LPs | E12: 46321 | F12: scheduled
A13: s12 | B13: cohort-2026 | C13: 12 | D13: Capstone Lab presentations | E13: 46328 | F13: scheduled

Sheet attendance_feedback
A1: fellow_id | B1: session_id | C1: attended | D1: feedback_submitted | E1: what_i_learned | F1: what_ill_apply | G1: feedback_submitted_at | H1: session_rating
A2: fellow-alexandra-smith | B2: s01 | C2: yes | D2: yes | E2: I came in thinking the funding gap was mostly about the amount of capital. The session made it clear that the gap is just as much about the type of capital, and that a lot of good businesses are being pushed toward equity that doesn't suit them. | F2: When I screen a deal I'm going to write one line on whether equity is actually the right instrument before I go further, and flag it to the partner if it isn't. | G2: 46253 | H2: 5
A3: fellow-alexandra-smith | B3: s02 | C3: yes | D3: yes | E3: I had been treating conviction as a feeling. The session reframed it as a set of explicit assumptions I can write down and test. | F3: Before our next IC, I'll draft a one-page thesis for each deal with the three assumptions that have to hold. | G3: 46260 | H3: 4
A4: fellow-alexandra-smith | B4: s03 | C4: yes | D4: yes | E4: Strong sourcing comes from being the first call for a small set of founders who trust you, rather than from volume. | F4: I'm picking two sectors and committing to one founder conversation a week in each, with no agenda attached. | G4: 46267 | H4: 5
A5: fellow-alexandra-smith | B5: s04 | C5: yes | D5: yes | E5: Diligence is only useful if it can change the answer. Half of what we ask for is to make ourselves feel thorough. | F5: For the deal I'm on now I'll list the three questions that could kill it and do those first, before the data room checklist. | G5: 46274 | H5: 5
A6: fellow-alexandra-smith | B6: s05 | C6: no | D6: no
A7: fellow-alexandra-smith | B7: s06 | C7: yes | D7: yes | E7: Reserves are a portfolio decision, not a deal decision. I hadn't realised how much our follow-on behaviour was being decided by whoever asked first. | F7: I want to build a simple reserves model for our current fund and bring it to our Monday pipeline meeting. | G7: 46288 | H7: 5
A8: fellow-alexandra-smith | B8: s07 | C8: yes | D8: no
A9: fellow-alexandra-smith | B9: s08 | C9: yes | D9: yes | E9: An IC memo is an argument, not a report. The best ones tell the committee what to believe and then show them why. | F9: My next memo will open with the recommendation and the two reasons it could be wrong, in the first paragraph. | G9: 46302 | H9: 5
A10: fellow-daniel-mensah | B10: s01 | C10: yes | D10: yes | E10: The numbers on how little capital reaches early-stage founders outside the big four markets were sobering. We talk about pan-African but our pipeline doesn't look like it. | F10: I'm going to map where our last 40 inbound deals came from and share it with the team. | G10: 46253 | H10: 5
A11: fellow-daniel-mensah | B11: s02 | C11: yes | D11: yes | E11: Separating "I like this founder" from "this is a good investment" sounds obvious but I do not do it consistently. | F11: Keep a decision log for every deal I recommend for or against, so I can check my calls in a year. | G11: 46260 | H11: 4
A12: fellow-daniel-mensah | B12: s03 | C12: no | D12: no
A13: fellow-daniel-mensah | B13: s04 | C13: yes | D13: no
A14: fellow-daniel-mensah | B14: s05 | C14: yes | D14: yes | E14: Structure is where you can protect the downside without fighting over the headline valuation. Most of our term sheets use the same template regardless of the deal. | G14: 46281 | H14: 4
A15: fellow-daniel-mensah | B15: s06 | C15: no | D15: no
A16: fellow-daniel-mensah | B16: s07 | C16: yes | D16: no
A17: fellow-daniel-mensah | B17: s08 | C17: yes | D17: yes | E17: The committee only remembers the first page. Everything else is there to answer questions, not to persuade. | F17: Rewrite our memo template so the first page is the decision, the risks and what we need to believe. | G17: 46302 | H17: 5
A18: fellow-amara-okafor | B18: s01 | C18: yes | D18: yes | E18: Hearing how other funds in the room think about the same market reminded me how narrow our own view can get. | F18: Set up a quarterly call with two other managers to compare notes on deals we both passed on. | G18: 46253 | H18: 5
A19: fellow-amara-okafor | B19: s02 | C19: yes | D19: yes | E19: The point that stuck was that conviction should be strongest about the few things that matter, and loose about everything else. | F19: In our next pipeline review I'll ask each of us to name the single assumption the deal depends on. | G19: 46260 | H19: 4
A20: fellow-amara-okafor | B20: s03 | C20: yes | D20: yes | E20: We rely almost entirely on our network for deal flow. It works, but it means we keep seeing the same kind of founder. | F20: Run a small open call for founders in two sectors we have never invested in and see what comes in. | G20: 46267 | H20: 5
A21: fellow-amara-okafor | B21: s04 | C21: yes | D21: yes | E21: Reference calls are most useful when you ask about the hard moments, not the highlights. | F21: Add three questions about how the founder handled a bad quarter to our reference call script. | G21: 46274 | H21: 5
A22: fellow-amara-okafor | B22: s05 | C22: yes | D22: yes | E22: Valuation in our market is less about comparables and more about what the next round will realistically look like. | F22: Model the next two rounds for every new deal before we agree a price. | G22: 46281 | H22: 4
A23: fellow-amara-okafor | B23: s06 | C23: yes | D23: yes | E23: We have been building a portfolio one deal at a time instead of deciding the shape of the portfolio first. | F23: Propose target ranges for cheque size and number of companies to our partners for the rest of the fund. | G23: 46288 | H23: 5
A24: fellow-amara-okafor | B24: s07 | C24: yes | D24: yes | E24: Founders want fewer, more useful conversations, not more support programmes. | F24: Ask each portfolio founder what one thing we could do this quarter that would actually help, and do it. | G24: 46295 | H24: 4
A25: fellow-amara-okafor | B25: s08 | C25: yes | D25: yes | E25: Writing clearly is a form of thinking clearly. If I can't say it in a paragraph, I don't understand it yet. | F25: Start every investment memo with a five-sentence summary and test it on a colleague before writing the rest. | G25: 46302 | H25: 5

Sheet capstone
A1: fellow_id | B1: recorded_at | C1: submitted | D1: submission_date | E1: submission_deadline | F1: submitted_on_time | G1: assessment_status | H1: assessment_score | I1: assessment_max_score | J1: detailed_feedback
A2: fellow-alexandra-smith | B2: 46297 | C2: yes | D2: 46296 | E2: 46297 | G2: pending
A3: fellow-daniel-mensah | B3: 46293 | C3: yes | D3: 46293 | E3: 46297 | G3: pending
A4: fellow-daniel-mensah | B4: 46300 | C4: yes | D4: 46293 | E4: 46297 | G4: complete | H4: 78 | I4: 100 | J4: DEMONSTRATION FEEDBACK. A clear, well-evidenced investment case with a realistic view of the exit route. The market sizing leans on top-down figures; the strongest submissions in the cohort built the case bottom-up from customer data. The risk section identifies the right issues but would be stronger with a view on how the structure mitigates each one.
A5: fellow-amara-okafor | B5: 46300 | C5: no | E5: 46356 | G5: not_started

Sheet self_updates
A1: fellow_id | B1: checkpoint_id | C1: activities_completed | D1: tracker_filled_in | E1: total_activities
A2: fellow-alexandra-smith | B2: cp-2026-2 | C2: 32 | D2: 33 | E2: 34
A3: fellow-daniel-mensah | B3: cp-2026-2 | C3: 23 | D3: 25 | E3: 34
A4: fellow-amara-okafor | B4: cp-2026-2 | C4: 18 | D4: 21 | E4: 34

Sheet checkpoints
A1: checkpoint_id | B1: cohort_id | C1: checkpoint_title | D1: reporting_date | E1: session_ids | F1: status
A2: cp-2026-1 | B2: cohort-2026 | C2: Checkpoint 1 | D2: 46273 | E2: s01;s02;s03;s04 | F2: published
A3: cp-2026-2 | B3: cohort-2026 | C3: Checkpoint 2 | D3: 46301 | E3: s01;s02;s03;s04;s05;s06;s07;s08 | F3: published

Sheet authorised_users
A1: user_id | B1: email | C1: name | D1: firm_id | E1: role | F1: access_status
A2: u1 | B2: managing.partner@example-capital.demo | C2: Managing Partner (demo) | D2: firm-example-capital | E2: firm_leader | F2: active
A3: u2 | B3: coo@example-capital.demo | C3: COO (demo) | D3: firm-example-capital | E3: firm_leader | F3: invited
A4: u3 | B4: partner@horizon-ventures.demo | C4: Partner (demo) | D4: firm-horizon-ventures | E4: firm_leader | F4: active
A5: u4 | B5: programme@included.vc.demo | C5: Programme team (demo) | E5: admin | F5: active

Sheet check_figures
A1: Check figures — calculated from the tabs above. Not imported; for checking only.
A2: Counts every session marked "held" and every attendance row, across the whole programme to date. The reports use the same rules per checkpoint.
A4: fellow_id | B4: Name | C4: Firm | D4: Sessions held | E4: Attended | F4: Attendance % | G4: Feedback submitted | H4: Feedback % | I4: Missing attendance rows | K4: Cohort averages
A5: =IF(fellows!A2="","",fellows!A2) | B5: =IF(A5="","",fellows!B2&" "&fellows!C2) | C5: =IF(A5="","",IFERROR(INDEX(firms!$B$2:$B$2000,MATCH(fellows!E2,firms!$A$2:$A$2000,0)),"(unknown firm)")) | D5: =IF(A5="","",COUNTIFS(sessions!$B$2:$B$2000,fellows!F2,sessions!$F$2:$F$2000,"held")+COUNTIFS(sessions!$B$2:$B$2000,fellows!F2,sessions!$F$2:$F$2000,"")) | E5: =IF(A5="","",COUNTIFS(attendance_feedback!$A$2:$A$2000,A5,attendance_feedback!$C$2:$C$2000,"yes")) | F5: =IF(A5="","",IF(D5=0,"—",E5/D5)) | G5: =IF(A5="","",COUNTIFS(attendance_feedback!$A$2:$A$2000,A5,attendance_feedback!$C$2:$C$2000,"yes",attendance_feedback!$D$2:$D$2000,"yes")) | H5: =IF(A5="","",IF(E5=0,"—",G5/E5)) | I5: =IF(A5="","",MAX(0,D5-COUNTIFS(attendance_feedback!$A$2:$A$2000,A5))) | K5: Attendance | L5: =IFERROR(AVERAGE(F5:F304),"—")
A6: =IF(fellows!A3="","",fellows!A3) | B6: =IF(A6="","",fellows!B3&" "&fellows!C3) | C6: =IF(A6="","",IFERROR(INDEX(firms!$B$2:$B$2000,MATCH(fellows!E3,firms!$A$2:$A$2000,0)),"(unknown firm)")) | D6: =IF(A6="","",COUNTIFS(sessions!$B$2:$B$2000,fellows!F3,sessions!$F$2:$F$2000,"held")+COUNTIFS(sessions!$B$2:$B$2000,fellows!F3,sessions!$F$2:$F$2000,"")) | E6: =IF(A6="","",COUNTIFS(attendance_feedback!$A$2:$A$2000,A6,attendance_feedback!$C$2:$C$2000,"yes")) | F6: =IF(A6="","",IF(D6=0,"—",E6/D6)) | G6: =IF(A6="","",COUNTIFS(attendance_feedback!$A$2:$A$2000,A6,attendance_feedback!$C$2:$C$2000,"yes",attendance_feedback!$D$2:$D$2000,"yes")) | H6: =IF(A6="","",IF(E6=0,"—",G6/E6)) | I6: =IF(A6="","",MAX(0,D6-COUNTIFS(attendance_feedback!$A$2:$A$2000,A6))) | K6: Feedback completion | L6: =IFERROR(AVERAGE(H5:H304),"—")
A7: =IF(fellows!A4="","",fellows!A4) | B7: =IF(A7="","",fellows!B4&" "&fellows!C4) | C7: =IF(A7="","",IFERROR(INDEX(firms!$B$2:$B$2000,MATCH(fellows!E4,firms!$A$2:$A$2000,0)),"(unknown firm)")) | D7: =IF(A7="","",COUNTIFS(sessions!$B$2:$B$2000,fellows!F4,sessions!$F$2:$F$2000,"held")+COUNTIFS(sessions!$B$2:$B$2000,fellows!F4,sessions!$F$2:$F$2000,"")) | E7: =IF(A7="","",COUNTIFS(attendance_feedback!$A$2:$A$2000,A7,attendance_feedback!$C$2:$C$2000,"yes")) | F7: =IF(A7="","",IF(D7=0,"—",E7/D7)) | G7: =IF(A7="","",COUNTIFS(attendance_feedback!$A$2:$A$2000,A7,attendance_feedback!$C$2:$C$2000,"yes",attendance_feedback!$D$2:$D$2000,"yes")) | H7: =IF(A7="","",IF(E7=0,"—",G7/E7)) | I7: =IF(A7="","",MAX(0,D7-COUNTIFS(attendance_feedback!$A$2:$A$2000,A7))) | K7: Average of each fellow's rate (fellows with no rate are left out).
A8: =IF(fellows!A5="","",fellows!A5) | B8: =IF(A8="","",fellows!B5&" "&fellows!C5) | C8: =IF(A8="","",IFERROR(INDEX(firms!$B$2:$B$2000,MATCH(fellows!E5,firms!$A$2:$A$2000,0)),"(unknown firm)")) | D8: =IF(A8="","",COUNTIFS(sessions!$B$2:$B$2000,fellows!F5,sessions!$F$2:$F$2000,"held")+COUNTIFS(sessions!$B$2:$B$2000,fellows!F5,sessions!$F$2:$F$2000,"")) | E8: =IF(A8="","",COUNTIFS(attendance_feedback!$A$2:$A$2000,A8,attendance_feedback!$C$2:$C$2000,"yes")) | F8: =IF(A8="","",IF(D8=0,"—",E8/D8)) | G8: =IF(A8="","",COUNTIFS(attendance_feedback!$A$2:$A$2000,A8,attendance_feedback!$C$2:$C$2000,"yes",attendance_feedback!$D$2:$D$2000,"yes")) | H8: =IF(A8="","",IF(E8=0,"—",G8/E8)) | I8: =IF(A8="","",MAX(0,D8-COUNTIFS(attendance_feedback!$A$2:$A$2000,A8)))
A9: =IF(fellows!A6="","",fellows!A6) | B9: =IF(A9="","",fellows!B6&" "&fellows!C6) | C9: =IF(A9="","",IFERROR(INDEX(firms!$B$2:$B$2000,MATCH(fellows!E6,firms!$A$2:$A$2000,0)),"(unknown firm)")) | D9: =IF(A9="","",COUNTIFS(sessions!$B$2:$B$2000,fellows!F6,sessions!$F$2:$F$2000,"held")+COUNTIFS(sessions!$B$2:$B$2000,fellows!F6,sessions!$F$2:$F$2000,"")) | E9: =IF(A9="","",COUNTIFS(attendance_feedback!$A$2:$A$2000,A9,attendance_feedback!$C$2:$C$2000,"yes")) | F9: =IF(A9="","",IF(D9=0,"—",E9/D9)) | G9: =IF(A9="","",COUNTIFS(attendance_feedback!$A$2:$A$2000,A9,attendance_feedback!$C$2:$C$2000,"yes",attendance_feedback!$D$2:$D$2000,"yes")) | H9: =IF(A9="","",IF(E9=0,"—",G9/E9)) | I9: =IF(A9="","",MAX(0,D9-COUNTIFS(attendance_feedback!$A$2:$A$2000,A9)))
A10: =IF(fellows!A7="","",fellows!A7) | B10: =IF(A10="","",fellows!B7&" "&fellows!C7) | C10: =IF(A10="","",IFERROR(INDEX(firms!$B$2:$B$2000,MATCH(fellows!E7,firms!$A$2:$A$2000,0)),"(unknown firm)")) | D10: =IF(A10="","",COUNTIFS(sessions!$B$2:$B$2000,fellows!F7,sessions!$F$2:$F$2000,"held")+COUNTIFS(sessions!$B$2:$B$2000,fellows!F7,sessions!$F$2:$F$2000,"")) | E10: =IF(A10="","",COUNTIFS(attendance_feedback!$A$2:$A$2000,A10,attendance_feedback!$C$2:$C$2000,"yes")) | F10: =IF(A10="","",IF(D10=0,"—",E10/D10)) | G10: =IF(A10="","",COUNTIFS(attendance_feedback!$A$2:$A$2000,A10,attendance_feedback!$C$2:$C$2000,"yes",attendance_feedback!$D$2:$D$2000,"yes")) | H10: =IF(A10="","",IF(E10=0,"—",G10/E10)) | I10: =IF(A10="","",MAX(0,D10-COUNTIFS(attendance_feedback!$A$2:$A$2000,A10)))
A11: =IF(fellows!A8="","",fellows!A8) | B11: =IF(A11="","",fellows!B8&" "&fellows!C8) | C11: =IF(A11="","",IFERROR(INDEX(firms!$B$2:$B$2000,MATCH(fellows!E8,firms!$A$2:$A$2000,0)),"(unknown firm)")) | D11: =IF(A11="","",COUNTIFS(sessions!$B$2:$B$2000,fellows!F8,sessions!$F$2:$F$2000,"held")+COUNTIFS(sessions!$B$2:$B$2000,fellows!F8,sessions!$F$2:$F$2000,"")) | E11: =IF(A11="","",COUNTIFS(attendance_feedback!$A$2:$A$2000,A11,attendance_feedback!$C$2:$C$2000,"yes")) | F11: =IF(A11="","",IF(D11=0,"—",E11/D11)) | G11: =IF(A11="","",COUNTIFS(attendance_feedback!$A$2:$A$2000,A11,attendance_feedback!$C$2:$C$2000,"yes",attendance_feedback!$D$2:$D$2000,"yes")) | H11: =IF(A11="","",IF(E11=0,"—",G11/E11)) | I11: =IF(A11="","",MAX(0,D11-COUNTIFS(attendance_feedback!$A$2:$A$2000,A11)))
A12: =IF(fellows!A9="","",fellows!A9) | B12: =IF(A12="","",fellows!B9&" "&fellows!C9) | C12: =IF(A12="","",IFERROR(INDEX(firms!$B$2:$B$2000,MATCH(fellows!E9,firms!$A$2:$A$2000,0)),"(unknown firm)")) | D12: =IF(A12="","",COUNTIFS(sessions!$B$2:$B$2000,fellows!F9,sessions!$F$2:$F$2000,"held")+COUNTIFS(sessions!$B$2:$B$2000,fellows!F9,sessions!$F$2:$F$2000,"")) | E12: =IF(A12="","",COUNTIFS(attendance_feedback!$A$2:$A$2000,A12,attendance_feedback!$C$2:$C$2000,"yes")) | F12: =IF(A12="","",IF(D12=0,"—",E12/D12)) | G12: =IF(A12="","",COUNTIFS(attendance_feedback!$A$2:$A$2000,A12,attendance_feedback!$C$2:$C$2000,"yes",attendance_feedback!$D$2:$D$2000,"yes")) | H12: =IF(A12="","",IF(E12=0,"—",G12/E12)) | I12: =IF(A12="","",MAX(0,D12-COUNTIFS(attendance_feedback!$A$2:$A$2000,A12)))
A13: =IF(fellows!A10="","",fellows!A10) | B13: =IF(A13="","",fellows!B10&" "&fellows!C10) | C13: =IF(A13="","",IFERROR(INDEX(firms!$B$2:$B$2000,MATCH(fellows!E10,firms!$A$2:$A$2000,0)),"(unknown firm)")) | D13: =IF(A13="","",COUNTIFS(sessions!$B$2:$B$2000,fellows!F10,sessions!$F$2:$F$2000,"held")+COUNTIFS(sessions!$B$2:$B$2000,fellows!F10,sessions!$F$2:$F$2000,"")) | E13: =IF(A13="","",COUNTIFS(attendance_feedback!$A$2:$A$2000,A13,attendance_feedback!$C$2:$C$2000,"yes")) | F13: =IF(A13="","",IF(D13=0,"—",E13/D13)) | G13: =IF(A13="","",COUNTIFS(attendance_feedback!$A$2:$A$2000,A13,attendance_feedback!$C$2:$C$2000,"yes",attendance_feedback!$D$2:$D$2000,"yes")) | H13: =IF(A13="","",IF(E13=0,"—",G13/E13)) | I13: =IF(A13="","",MAX(0,D13-COUNTIFS(attendance_feedback!$A$2:$A$2000,A13)))
A14: =IF(fellows!A11="","",fellows!A11) | B14: =IF(A14="","",fellows!B11&" "&fellows!C11) | C14: =IF(A14="","",IFERROR(INDEX(firms!$B$2:$B$2000,MATCH(fellows!E11,firms!$A$2:$A$2000,0)),"(unknown firm)")) | D14: =IF(A14="","",COUNTIFS(sessions!$B$2:$B$2000,fellows!F11,sessions!$F$2:$F$2000,"held")+COUNTIFS(sessions!$B$2:$B$2000,fellows!F11,sessions!$F$2:$F$2000,"")) | E14: =IF(A14="","",COUNTIFS(attendance_feedback!$A$2:$A$2000,A14,attendance_feedback!$C$2:$C$2000,"yes")) | F14: =IF(A14="","",IF(D14=0,"—",E14/D14)) | G14: =IF(A14="","",COUNTIFS(attendance_feedback!$A$2:$A$2000,A14,attendance_feedback!$C$2:$C$2000,"yes",attendance_feedback!$D$2:$D$2000,"yes")) | H14: =IF(A14="","",IF(E14=0,"—",G14/E14)) | I14: =IF(A14="","",MAX(0,D14-COUNTIFS(attendance_feedback!$A$2:$A$2000,A14)))
A15: =IF(fellows!A12="","",fellows!A12) | B15: =IF(A15="","",fellows!B12&" "&fellows!C12) | C15: =IF(A15="","",IFERROR(INDEX(firms!$B$2:$B$2000,MATCH(fellows!E12,firms!$A$2:$A$2000,0)),"(unknown firm)")) | D15: =IF(A15="","",COUNTIFS(sessions!$B$2:$B$2000,fellows!F12,sessions!$F$2:$F$2000,"held")+COUNTIFS(sessions!$B$2:$B$2000,fellows!F12,sessions!$F$2:$F$2000,"")) | E15: =IF(A15="","",COUNTIFS(attendance_feedback!$A$2:$A$2000,A15,attendance_feedback!$C$2:$C$2000,"yes")) | F15: =IF(A15="","",IF(D15=0,"—",E15/D15)) | G15: =IF(A15="","",COUNTIFS(attendance_feedback!$A$2:$A$2000,A15,attendance_feedback!$C$2:$C$2000,"yes",attendance_feedback!$D$2:$D$2000,"yes")) | H15: =IF(A15="","",IF(E15=0,"—",G15/E15)) | I15: =IF(A15="","",MAX(0,D15-COUNTIFS(attendance_feedback!$A$2:$A$2000,A15)))
A16: =IF(fellows!A13="","",fellows!A13) | B16: =IF(A16="","",fellows!B13&" "&fellows!C13) | C16: =IF(A16="","",IFERROR(INDEX(firms!$B$2:$B$2000,MATCH(fellows!E13,firms!$A$2:$A$2000,0)),"(unknown firm)")) | D16: =IF(A16="","",COUNTIFS(sessions!$B$2:$B$2000,fellows!F13,sessions!$F$2:$F$2000,"held")+COUNTIFS(sessions!$B$2:$B$2000,fellows!F13,sessions!$F$2:$F$2000,"")) | E16: =IF(A16="","",COUNTIFS(attendance_feedback!$A$2:$A$2000,A16,attendance_feedback!$C$2:$C$2000,"yes")) | F16: =IF(A16="","",IF(D16=0,"—",E16/D16)) | G16: =IF(A16="","",COUNTIFS(attendance_feedback!$A$2:$A$2000,A16,attendance_feedback!$C$2:$C$2000,"yes",attendance_feedback!$D$2:$D$2000,"yes")) | H16: =IF(A16="","",IF(E16=0,"—",G16/E16)) | I16: =IF(A16="","",MAX(0,D16-COUNTIFS(attendance_feedback!$A$2:$A$2000,A16)))
A17: =IF(fellows!A14="","",fellows!A14) | B17: =IF(A17="","",fellows!B14&" "&fellows!C14) | C17: =IF(A17="","",IFERROR(INDEX(firms!$B$2:$B$2000,MATCH(fellows!E14,firms!$A$2:$A$2000,0)),"(unknown firm)")) | D17: =IF(A17="","",COUNTIFS(sessions!$B$2:$B$2000,fellows!F14,sessions!$F$2:$F$2000,"held")+COUNTIFS(sessions!$B$2:$B$2000,fellows!F14,sessions!$F$2:$F$2000,"")) | E17: =IF(A17="","",COUNTIFS(attendance_feedback!$A$2:$A$2000,A17,attendance_feedback!$C$2:$C$2000,"yes")) | F17: =IF(A17="","",IF(D17=0,"—",E17/D17)) | G17: =IF(A17="","",COUNTIFS(attendance_feedback!$A$2:$A$2000,A17,attendance_feedback!$C$2:$C$2000,"yes",attendance_feedback!$D$2:$D$2000,"yes")) | H17: =IF(A17="","",IF(E17=0,"—",G17/E17)) | I17: =IF(A17="","",MAX(0,D17-COUNTIFS(attendance_feedback!$A$2:$A$2000,A17)))
A18: =IF(fellows!A15="","",fellows!A15) | B18: =IF(A18="","",fellows!B15&" "&fellows!C15) | C18: =IF(A18="","",IFERROR(INDEX(firms!$B$2:$B$2000,MATCH(fellows!E15,firms!$A$2:$A$2000,0)),"(unknown firm)")) | D18: =IF(A18="","",COUNTIFS(sessions!$B$2:$B$2000,fellows!F15,sessions!$F$2:$F$2000,"held")+COUNTIFS(sessions!$B$2:$B$2000,fellows!F15,sessions!$F$2:$F$2000,"")) | E18: =IF(A18="","",COUNTIFS(attendance_feedback!$A$2:$A$2000,A18,attendance_feedback!$C$2:$C$2000,"yes")) | F18: =IF(A18="","",IF(D18=0,"—",E18/D18)) | G18: =IF(A18="","",COUNTIFS(attendance_feedback!$A$2:$A$2000,A18,attendance_feedback!$C$2:$C$2000,"yes",attendance_feedback!$D$2:$D$2000,"yes")) | H18: =IF(A18="","",IF(E18=0,"—",G18/E18)) | I18: =IF(A18="","",MAX(0,D18-COUNTIFS(attendance_feedback!$A$2:$A$2000,A18)))
A19: =IF(fellows!A16="","",fellows!A16) | B19: =IF(A19="","",fellows!B16&" "&fellows!C16) | C19: =IF(A19="","",IFERROR(INDEX(firms!$B$2:$B$2000,MATCH(fellows!E16,firms!$A$2:$A$2000,0)),"(unknown firm)")) | D19: =IF(A19="","",COUNTIFS(sessions!$B$2:$B$2000,fellows!F16,sessions!$F$2:$F$2000,"held")+COUNTIFS(sessions!$B$2:$B$2000,fellows!F16,sessions!$F$2:$F$2000,"")) | E19: =IF(A19="","",COUNTIFS(attendance_feedback!$A$2:$A$2000,A19,attendance_feedback!$C$2:$C$2000,"yes")) | F19: =IF(A19="","",IF(D19=0,"—",E19/D19)) | G19: =IF(A19="","",COUNTIFS(attendance_feedback!$A$2:$A$2000,A19,attendance_feedback!$C$2:$C$2000,"yes",attendance_feedback!$D$2:$D$2000,"yes")) | H19: =IF(A19="","",IF(E19=0,"—",G19/E19)) | I19: =IF(A19="","",MAX(0,D19-COUNTIFS(attendance_feedback!$A$2:$A$2000,A19)))
... A304: =IF(fellows!A301="","",fellows!A301) | B304: =IF(A304="","",fellows!B301&" "&fellows!C301) | C304: =IF(A304="","",IFERROR(INDEX(firms!$B$2:$B$2000,MATCH(fellows!E301,firms!$A$2:$A$2000,0)),"(unknown firm)")) | D304: =IF(A304="","",COUNTIFS(sessions!$B$2:$B$2000,fellows!F301,sessions!$F$2:$F$2000,"held")+COUNTIFS(sessions!$B$2:$B$2000,fellows!F301,sessions!$F$2:$F$2000,"")) | E304: =IF(A304="","",COUNTIFS(attendance_feedback!$A$2:$A$2000,A304,attendance_feedback!$C$2:$C$2000,"yes")) | F304: =IF(A304="","",IF(D304=0,"—",E304/D304)) | G304: =IF(A304="","",COUNTIFS(attendance_feedback!$A$2:$A$2000,A304,attendance_feedback!$C$2:$C$2000,"yes",attendance_feedback!$D$2:$D$2000,"yes")) | H304: =IF(A304="","",IF(E304=0,"—",G304/E304)) | I304: =IF(A304="","",MAX(0,D304-COUNTIFS(attendance_feedback!$A$2:$A$2000,A304)))
